KoaZhongwenWendang/README.md
KoaZhongwenWendang/__init__.py
KoaZhongwenWendang/__main__.py
KoaZhongwenWendang/file.epub
KoaZhongwenWendang/index.html
KoaZhongwenWendang/css/__init__.py
KoaZhongwenWendang/css/annotations.css
KoaZhongwenWendang/css/main.css
KoaZhongwenWendang/css/normalize.css
KoaZhongwenWendang/css/popup.css
KoaZhongwenWendang/font/__init__.py
KoaZhongwenWendang/font/fontello.eot
KoaZhongwenWendang/font/fontello.svg
KoaZhongwenWendang/font/fontello.ttf
KoaZhongwenWendang/font/fontello.woff
KoaZhongwenWendang/img/__init__.py
KoaZhongwenWendang/img/annotator-glyph-sprite.png
KoaZhongwenWendang/img/annotator-icon-sprite.png
KoaZhongwenWendang/img/apple-touch-icon.png
KoaZhongwenWendang/img/cancelfullscreen.png
KoaZhongwenWendang/img/close.png
KoaZhongwenWendang/img/fullscreen.png
KoaZhongwenWendang/img/loader.gif
KoaZhongwenWendang/img/menu-icon.png
KoaZhongwenWendang/img/save.png
KoaZhongwenWendang/img/saved.png
KoaZhongwenWendang/img/settings-s.png
KoaZhongwenWendang/img/settings.png
KoaZhongwenWendang/img/star.png
KoaZhongwenWendang/js/__init__.py
KoaZhongwenWendang/js/epub.js
KoaZhongwenWendang/js/epub.min.js
KoaZhongwenWendang/js/epub.min.map
KoaZhongwenWendang/js/hooks.min.js
KoaZhongwenWendang/js/hooks.min.map
KoaZhongwenWendang/js/reader.js
KoaZhongwenWendang/js/reader.js.map
KoaZhongwenWendang/js/reader.min.js
KoaZhongwenWendang/js/reader.min.map
KoaZhongwenWendang/js/hooks/__init__.py
KoaZhongwenWendang/js/hooks/extensions/__init__.py
KoaZhongwenWendang/js/hooks/extensions/highlight.js
KoaZhongwenWendang/js/libs/__init__.py
KoaZhongwenWendang/js/libs/jquery.min.js
KoaZhongwenWendang/js/libs/localforage.min.js
KoaZhongwenWendang/js/libs/screenfull.js
KoaZhongwenWendang/js/libs/screenfull.min.js
KoaZhongwenWendang/js/libs/zip.min.js
KoaZhongwenWendang/js/plugins/__init__.py
KoaZhongwenWendang/js/plugins/hypothesis.js
KoaZhongwenWendang/js/plugins/search.js
koa_zhongwen_wendang-2024.3.1.0.dist-info/METADATA
koa_zhongwen_wendang-2024.3.1.0.dist-info/WHEEL
koa_zhongwen_wendang-2024.3.1.0.dist-info/entry_points.txt
koa_zhongwen_wendang-2024.3.1.0.dist-info/top_level.txt
koa_zhongwen_wendang-2024.3.1.0.dist-info/RECORD
